pyltp.cpython-38-darwin.so
pyltp_binary-0.2.1.0.dist-info/METADATA
pyltp_binary-0.2.1.0.dist-info/WHEEL
pyltp_binary-0.2.1.0.dist-info/top_level.txt
pyltp_binary-0.2.1.0.dist-info/RECORD
